miarec_ftpfs/__init__.py
miarec_ftpfs/_ftp_parse.py
miarec_ftpfs/_version.txt
miarec_ftpfs/ftp_tls.py
miarec_ftpfs/ftpfs.py
miarec_ftpfs/opener.py
miarec_ftpfs/py.typed
miarec_ftpfs-2025.5.27.dist-info/licenses/LICENSE
miarec_ftpfs-2025.5.27.dist-info/METADATA
miarec_ftpfs-2025.5.27.dist-info/WHEEL
miarec_ftpfs-2025.5.27.dist-info/entry_points.txt
miarec_ftpfs-2025.5.27.dist-info/top_level.txt
miarec_ftpfs-2025.5.27.dist-info/zip-safe
miarec_ftpfs-2025.5.27.dist-info/RECORD
