Metadata-Version: 2.4
Name: miarec_ftpfs
Version: 2025.5.27
Summary: FTP filesystem for PyFilesystem2
Home-page: https://github.com/miarec/miarec_ftpfs
Author: MiaRec
Author-email: support@miarec.com
License: MIT
Project-URL: Bug Tracker, https://github.com/miarec/miarec_ftpfs/issues
Project-URL: Builds, https://github.com/miarec/miarec_ftpfs/actions
Keywords: filesystem,Pyfilesystem2,ftp,ftps
Platform: any
Classifier: Development Status :: 5 - Production/Stable
Classifier: Intended Audience :: Developers
Classifier: License :: OSI Approved :: MIT License
Classifier: Operating System :: OS Independent
Classifier: Programming Language :: Python
Classifier: Programming Language :: Python :: 3.6
Classifier: Programming Language :: Python :: 3.7
Classifier: Programming Language :: Python :: 3.8
Classifier: Programming Language :: Python :: 3.9
Classifier: Programming Language :: Python :: 3.10
Classifier: Programming Language :: Python :: 3.11
Classifier: Topic :: System :: Filesystems
Requires-Python: >=3.6
License-File: LICENSE
Requires-Dist: fs~=2.4
Requires-Dist: setuptools>=38.3.0
Provides-Extra: test
Requires-Dist: pytest~=7.4; extra == "test"
Requires-Dist: pytest-cov~=4.1; extra == "test"
Requires-Dist: pyftpdlib~=1.5; extra == "test"
Requires-Dist: psutil~=6.0; extra == "test"
Requires-Dist: PyOpenSSL~=23.3; extra == "test"
Requires-Dist: cryptography~=41.0; extra == "test"
Dynamic: license-file
